collective.behavior.banner-2.0-py3.11-nspkg.pth
collective/behavior/banner/__init__.py
collective/behavior/banner/banner.py
collective/behavior/banner/configure.zcml
collective/behavior/banner/interfaces.py
collective/behavior/banner/setuphandlers.py
collective/behavior/banner/slider.py
collective/behavior/banner/testing.py
collective/behavior/banner/testing.zcml
collective/behavior/banner/upgradehandlers.py
collective/behavior/banner/browser/__init__.py
collective/behavior/banner/browser/banner.pt
collective/behavior/banner/browser/configure.zcml
collective/behavior/banner/browser/controlpanel.py
collective/behavior/banner/browser/slider.pt
collective/behavior/banner/browser/viewlets.py
collective/behavior/banner/browser/static/.gitkeep
collective/behavior/banner/browser/static/banner.css
collective/behavior/banner/browser/static/responsiveslides.css
collective/behavior/banner/browser/static/responsiveslides.min.js
collective/behavior/banner/profiles/default/browserlayer.xml
collective/behavior/banner/profiles/default/catalog.xml
collective/behavior/banner/profiles/default/collectivebehaviorbanner_default.txt
collective/behavior/banner/profiles/default/controlpanel.xml
collective/behavior/banner/profiles/default/metadata.xml
collective/behavior/banner/profiles/default/registry.xml
collective/behavior/banner/profiles/uninstall/browserlayer.xml
collective/behavior/banner/profiles/uninstall/catalog.xml
collective/behavior/banner/profiles/uninstall/collectivebehaviorbanner_uninstall.txt
collective/behavior/banner/profiles/uninstall/registry.xml
collective/behavior/banner/tests/__init__.py
collective/behavior/banner/tests/test_field.py
collective/behavior/banner/tests/test_setup.py
collective.behavior.banner-2.0.dist-info/METADATA
collective.behavior.banner-2.0.dist-info/WHEEL
collective.behavior.banner-2.0.dist-info/entry_points.txt
collective.behavior.banner-2.0.dist-info/namespace_packages.txt
collective.behavior.banner-2.0.dist-info/top_level.txt
collective.behavior.banner-2.0.dist-info/RECORD
