Metadata-Version: 2.1
Name: collective.behavior.banner
Version: 2.0
Summary: An add-on for Plone
Home-page: https://pypi.python.org/pypi/collective.behavior.banner
Author: Philip Bauer
Author-email: bauer@starzel.de
License: GPL version 2
Keywords: Python Plone
Classifier: Environment :: Web Environment
Classifier: Framework :: Plone
Classifier: Framework :: Plone :: 6.0
Classifier: Programming Language :: Python
Classifier: Programming Language :: Python :: 3.8
Classifier: Programming Language :: Python :: 3.9
Classifier: Programming Language :: Python :: 3.10
Classifier: Programming Language :: Python :: 3.11
Classifier: Operating System :: OS Independent
Classifier: License :: OSI Approved :: GNU General Public License v2 (GPLv2)
Requires-Dist: plone.api
Requires-Dist: z3c.jbot
Requires-Dist: six
Provides-Extra: test
Requires-Dist: plone.app.testing ; extra == 'test'
Requires-Dist: plone.testing (>=5.0.0) ; extra == 'test'
Requires-Dist: plone.app.contenttypes ; extra == 'test'
Requires-Dist: plone.app.robotframework[debug] ; extra == 'test'
